{
  "scenario": 2,
  "n_episodes": 30,
  "astar": {
    "survival_rate": {
      "mean": 0.7733,
      "std": 0.1545,
      "min": 0.375,
      "max": 1.0
    },
    "escaped_A": {
      "mean": 3.9667,
      "std": 2.4424,
      "min": 0.0,
      "max": 10.0
    },
    "escaped_B": {
      "mean": 26.9667,
      "std": 6.9401,
      "min": 13.0,
      "max": 38.0
    },
    "dead": {
      "mean": 9.0667,
      "std": 6.1803,
      "min": 0.0,
      "max": 25.0
    },
    "steps_taken": {
      "mean": 110.1,
      "std": 18.1757,
      "min": 81.0,
      "max": 140.0
    }
  },
  "ppo": {
    "survival_rate": {
      "mean": 0.8867,
      "std": 0.0451,
      "min": 0.775,
      "max": 0.95
    },
    "escaped_A": {
      "mean": 3.7333,
      "std": 2.7072,
      "min": 0.0,
      "max": 11.0
    },
    "escaped_B": {
      "mean": 31.7333,
      "std": 3.346,
      "min": 23.0,
      "max": 37.0
    },
    "dead": {
      "mean": 4.5333,
      "std": 1.8025,
      "min": 2.0,
      "max": 9.0
    },
    "steps_taken": {
      "mean": 93.5667,
      "std": 11.8425,
      "min": 70.0,
      "max": 111.0
    }
  }
}